[
  {
    "full_name": "karanpratapsingh/learn-go",
    "stargazers_count": 770,
    "open_issues_count": 0,
    "forks_count": 82
  },
  {
    "full_name": "metalcorpe/payshield-rest-gopher",
    "stargazers_count": 1,
    "open_issues_count": 5,
    "forks_count": 0
  },
  {
    "full_name": "nitefood/asn",
    "stargazers_count": 1091,
    "open_issues_count": 2,
    "forks_count": 136
  },
  {
    "full_name": "ultrafunkamsterdam/undetected-chromedriver",
    "stargazers_count": 7113,
    "open_issues_count": 858,
    "forks_count": 956
  },
  {
    "full_name": "rfc1036/whois",
    "stargazers_count": 427,
    "open_issues_count": 14,
    "forks_count": 109
  },
  {
    "full_name": "degrigis/awesome-angr",
    "stargazers_count": 131,
    "open_issues_count": 0,
    "forks_count": 6
  }
]